pulpcore/__init__.py
pulpcore/client/__init__.py
pulpcore/client/pulp_rpm/__init__.py
pulpcore/client/pulp_rpm/api_client.py
pulpcore/client/pulp_rpm/api_response.py
pulpcore/client/pulp_rpm/configuration.py
pulpcore/client/pulp_rpm/exceptions.py
pulpcore/client/pulp_rpm/py.typed
pulpcore/client/pulp_rpm/rest.py
pulpcore/client/pulp_rpm/api/__init__.py
pulpcore/client/pulp_rpm/api/acs_rpm_api.py
pulpcore/client/pulp_rpm/api/content_advisories_api.py
pulpcore/client/pulp_rpm/api/content_distribution_trees_api.py
pulpcore/client/pulp_rpm/api/content_modulemd_defaults_api.py
pulpcore/client/pulp_rpm/api/content_modulemd_obsoletes_api.py
pulpcore/client/pulp_rpm/api/content_modulemds_api.py
pulpcore/client/pulp_rpm/api/content_packagecategories_api.py
pulpcore/client/pulp_rpm/api/content_packageenvironments_api.py
pulpcore/client/pulp_rpm/api/content_packagegroups_api.py
pulpcore/client/pulp_rpm/api/content_packagelangpacks_api.py
pulpcore/client/pulp_rpm/api/content_packages_api.py
pulpcore/client/pulp_rpm/api/content_repo_metadata_files_api.py
pulpcore/client/pulp_rpm/api/distributions_rpm_api.py
pulpcore/client/pulp_rpm/api/publications_rpm_api.py
pulpcore/client/pulp_rpm/api/remotes_rpm_api.py
pulpcore/client/pulp_rpm/api/remotes_uln_api.py
pulpcore/client/pulp_rpm/api/repositories_rpm_api.py
pulpcore/client/pulp_rpm/api/repositories_rpm_versions_api.py
pulpcore/client/pulp_rpm/api/rpm_comps_api.py
pulpcore/client/pulp_rpm/api/rpm_copy_api.py
pulpcore/client/pulp_rpm/api/rpm_prune_api.py
pulpcore/client/pulp_rpm/models/__init__.py
pulpcore/client/pulp_rpm/models/addon_response.py
pulpcore/client/pulp_rpm/models/artifact_response.py
pulpcore/client/pulp_rpm/models/async_operation_response.py
pulpcore/client/pulp_rpm/models/checksum_response.py
pulpcore/client/pulp_rpm/models/compression_type_enum.py
pulpcore/client/pulp_rpm/models/content_summary_response.py
pulpcore/client/pulp_rpm/models/copy.py
pulpcore/client/pulp_rpm/models/image_response.py
pulp_rpm_client-3.34.0.dist-info/METADATA
pulp_rpm_client-3.34.0.dist-info/WHEEL
pulp_rpm_client-3.34.0.dist-info/top_level.txt
pulp_rpm_client-3.34.0.dist-info/RECORD
